nyuv2/NYUv2Dataset.py
nyuv2/__init__.py
nyu_depth_v2-0.0.3.dist-info/METADATA
nyu_depth_v2-0.0.3.dist-info/WHEEL
nyu_depth_v2-0.0.3.dist-info/top_level.txt
nyu_depth_v2-0.0.3.dist-info/RECORD
