Metadata-Version: 2.1
Name: nyu-depth-v2
Version: 0.0.3
Summary: NYUv2 Dataset for PyTorch.
Home-page: https://github.com/BeomseoChoi/NYUv2_Dataset_Pytorch.git
Author: Beomseo Choi
Author-email: beomseo0707@gmail.com
Keywords: beomseo choi,beomseo0707,nyuv2 datasets,nyuv2,nyu depth
Classifier: Programming Language :: Python :: 3.6
Classifier: Programming Language :: Python :: 3.7
Classifier: Programming Language :: Python :: 3.8
Classifier: Programming Language :: Python :: 3.9
Classifier: Programming Language :: Python :: 3.10
Classifier: Programming Language :: Python :: 3.11
Requires-Python: >=3.6
Requires-Dist: torch
Requires-Dist: torchvision
Requires-Dist: numpy
Requires-Dist: opencv-python
Requires-Dist: h5py
Requires-Dist: tqdm
Requires-Dist: einops
Requires-Dist: pathlib
